pconvert_rust/__init__.py
pconvert_rust/pconvert_rust.cpython-38-darwin.so
pconvert_rust/test/__init__.py
pconvert_rust/test/global.py
pconvert_rust-0.1.1.dist-info/LICENSE
pconvert_rust-0.1.1.dist-info/METADATA
pconvert_rust-0.1.1.dist-info/WHEEL
pconvert_rust-0.1.1.dist-info/top_level.txt
pconvert_rust-0.1.1.dist-info/RECORD
