Metadata-Version: 2.1
Name: pconvert-rust
Version: 0.1.1
Summary: PNG Convert Rust
Home-page: https://www.platforme.com
Author: Platforme International
Author-email: development@platforme.com
License: Apache License, Version 2.0
Keywords: pconvert rust fast
Platform: UNKNOWN
Classifier: Development Status :: 5 - Production/Stable
Classifier: Topic :: Utilities
Classifier: License :: OSI Approved :: Apache Software License
Classifier: Operating System :: OS Independent
Classifier: Programming Language :: Python
Classifier: Programming Language :: Python :: 3.5
Classifier: Programming Language :: Python :: 3.6
Classifier: Programming Language :: Python :: 3.7
